trampolim/_build.py
trampolim/_metadata.py
trampolim/types.py
trampolim/_sdist.py
trampolim/_wheel.py
trampolim/_tasks.py
trampolim/__main__.py
trampolim/__init__.py
trampolim-0.1.0.dist-info/METADATA
trampolim-0.1.0.dist-info/WHEEL
trampolim-0.1.0.dist-info/entrypoints.txt
trampolim-0.1.0.dist-info/RECORD
