Metadata-Version: 2.1
Name: trampolim
Version: 0.1.0
Summary: A modern Python build backend
Keywords: build pep517 package packaging
Home-page: https://github.com/FFY00/trampolim
Author-Email: Filipe Laíns <lains@riseup.net>
Classifier: Development Status :: 4 - Beta
Classifier: Programming Language :: Python
Project-URL: Homepage, https://github.com/FFY00/trampolim
Project-URL: Repository, https://github.com/FFY00/trampolim
Project-URL: Documentation, https://trampolim.readthedocs.io
Project-URL: Changelog, https://trampolim.readthedocs.io/en/latest/changelog.html
Requires-Python: >=3.7
Requires-Dist: tomli>=1.0.0
Requires-Dist: packaging
Requires-Dist: pep621>=0.4.0
Requires-Dist: backports.cached-property; python_version < "3.8"
Requires-Dist: wheel; extra == "test"
Requires-Dist: pytest>=3.9.1; extra == "test"
Requires-Dist: pytest-cov; extra == "test"
Requires-Dist: pytest-mock; extra == "test"
Requires-Dist: furo>=2021.04.11b34; extra == "docs"
Requires-Dist: sphinx~=3.0; extra == "docs"
Requires-Dist: sphinx-autodoc-typehints>=1.10; extra == "docs"
Provides-Extra: test
Provides-Extra: docs
